python_simple_tasks/__init__.py
python_simple_tasks/cli.py
python_simple_tasks/scheduler.py
python_simple_tasks/utils.py
python_simple_tasks/tests/__init__.py
python_simple_tasks/tests/settings.py
python_simple_tasks/tests/test_cli.py
python_simple_tasks/tests/test_scheduler.py
python_simple_tasks/tests/test_utils.py
python_simple_tasks-1.0.0.dist-info/METADATA
python_simple_tasks-1.0.0.dist-info/WHEEL
python_simple_tasks-1.0.0.dist-info/entry_points.txt
python_simple_tasks-1.0.0.dist-info/top_level.txt
python_simple_tasks-1.0.0.dist-info/RECORD
