Metadata-Version: 2.2
Name: python-simple-tasks
Version: 1.0.0
Summary: A lightweight Python task scheduler and processor using PostgreSQL.
Home-page: https://github.com/loganhenson/python-simple-tasks
Author: Logan Henson
Author-email: logan@loganhenson.com
Classifier: Programming Language :: Python :: 3
Classifier: License :: OSI Approved :: MIT License
Classifier: Operating System :: OS Independent
Requires-Python: >=3.7
Requires-Dist: psycopg2-binary
Dynamic: author
Dynamic: author-email
Dynamic: classifier
Dynamic: description
Dynamic: description-content-type
Dynamic: home-page
Dynamic: requires-dist
Dynamic: requires-python
Dynamic: summary
